Metadata-Version: 2.1
Name: skilletcli
Version: 3.0.0
Summary: Packages and CLI tools for interacting with hosted Skillets.
Home-page: https://github.com/adambaumeister/skilletcli
Author: abaumeister
Author-email: abaumeister@paloaltonetworks.com
License: Apache 2.0
Download-URL: https://github.com/adambaumeister/skilletcli/releases/latest/download/skilletcli.tar.gz
Platform: UNKNOWN
Classifier: Development Status :: 5 - Production/Stable
Classifier: Programming Language :: Python :: 3.6
Classifier: Programming Language :: Python :: 3.7
